{
  "name": "clean-code",
  "type": "skill",
  "description": "Use when writing, reviewing, or refactoring code for maintainability and readability. Triggers on code reviews, naming discussions, function design, error handling, and test writing. Based on Robert C. Martin's Clean Code handbook with modern corrections.",
  "domain": "languages",
  "subdomain": "typescript",
  "specialty": "functional patterns",
  "quality": 5,
  "qualityReason": "Highly actionable coding principles",
  "bundleHints": [
    "typescript-stack",
    "code-quality"
  ],
  "tags": [
    "best-practices",
    "clean-code",
    "code-quality",
    "functional",
    "maintainability",
    "refactoring",
    "typescript"
  ],
  "capabilities": [
    "Explains DRY principle with TypeScript code examples",
    "Demonstrates KISS principle through refactoring examples",
    "Shows YAGNI principle with practical scenarios"
  ],
  "author": "DoubleslashSE",
  "supportedTools": [],
  "limitations": [],
  "useCases": [],
  "promptTemplates": [],
  "bestPractices": [],
  "antiPatterns": [],
  "faq": [],
  "seoKeywords": [],
  "dependencies": []
}