{
  "name": "design-system-generator",
  "type": "skill",
  "description": "Design system generator that matches natural language descriptions to design trends. Expert in Swiss Modern, Neobrutalism, Glassmorphism, and 20+ other design trends. Includes trend matching scripts and comprehensive design pattern library.",
  "domain": "design",
  "subdomain": "design-systems",
  "specialty": "trend matching",
  "quality": 4,
  "qualityReason": "Creative, trend-aware generation",
  "bundleHints": [
    "design-system",
    "creative-design"
  ],
  "tags": [
    "design trends",
    "generator",
    "glassmorphism",
    "natural language",
    "neobrutalism",
    "swiss modern"
  ],
  "capabilities": [],
  "author": "",
  "supportedTools": [],
  "limitations": [],
  "useCases": [],
  "promptTemplates": [],
  "bestPractices": [],
  "antiPatterns": [],
  "faq": [],
  "seoKeywords": [],
  "dependencies": []
}