{
  "name": "feature-manifest",
  "type": "skill",
  "description": "Manage feature manifests for code traceability. Use when creating new features, updating existing features, checking feature health, or exploring the feature-to-code relationship. Activates for manifest validation, feature creation, changelog updates, and traceability queries.",
  "domain": "productivity",
  "subdomain": "communication",
  "specialty": "structured feedback",
  "quality": 5,
  "qualityReason": "Actionable communication framework",
  "bundleHints": [
    "leadership-tools",
    "team-workflow"
  ],
  "tags": [
    "communication",
    "difficult-conversations",
    "feedback",
    "leadership",
    "performance-review",
    "sbi"
  ],
  "capabilities": [],
  "author": "",
  "supportedTools": [],
  "limitations": [],
  "useCases": [],
  "promptTemplates": [],
  "bestPractices": [],
  "antiPatterns": [],
  "faq": [],
  "seoKeywords": [],
  "dependencies": []
}