{
  "name": "nocodb",
  "type": "skill",
  "description": "Access and manage NocoDB databases via REST APIs. Free plans support bases, tables, fields, records, links, filters, sorts, and attachments. Enterprise plans add workspaces, views, scripts, teams, and collaboration features.",
  "domain": "data",
  "subdomain": "databases",
  "specialty": "NocoDB management",
  "quality": 4,
  "qualityReason": "Specific database platform",
  "bundleHints": [
    "no-code-database",
    "data-management"
  ],
  "tags": [
    "database",
    "enterprise",
    "nocodb",
    "records",
    "rest-api",
    "tables"
  ],
  "capabilities": [],
  "author": "",
  "supportedTools": [],
  "limitations": [],
  "useCases": [],
  "promptTemplates": [],
  "bestPractices": [],
  "antiPatterns": [],
  "faq": [],
  "seoKeywords": [],
  "dependencies": []
}