{
  "name": "ruby-refactor",
  "type": "skill",
  "description": "Ruby refactoring guidelines from community best practices. This skill should be used when refactoring, reviewing, or restructuring Ruby code to improve design, readability, and maintainability. Triggers on tasks involving code smells, method extraction, conditional simplification, coupling reduction, design patterns, or Ruby idiom adoption.",
  "domain": "languages",
  "subdomain": "ruby",
  "specialty": "code refactoring",
  "quality": 5,
  "qualityReason": "Specific, community-driven",
  "bundleHints": [
    "ruby-stack",
    "code-quality"
  ],
  "tags": [
    "best-practices",
    "design",
    "maintainability",
    "readability",
    "refactoring",
    "ruby"
  ],
  "capabilities": [],
  "author": "",
  "supportedTools": [],
  "limitations": [],
  "useCases": [],
  "promptTemplates": [],
  "bestPractices": [],
  "antiPatterns": [],
  "faq": [],
  "seoKeywords": [],
  "dependencies": []
}